{
  "main": {
    "id": "eecb433279ac33e2",
    "type": "split",
    "children": [
      {
        "id": "be92d395673d2686",
        "type": "tabs",
        "children": [
          {
            "id": "efdfb0bb40673fb2",
            "type": "leaf",
            "state": {
              "type": "markdown",
              "state": {
                "file": "Fac/Les bases en C++.md",
                "mode": "source",
                "source": false
              }
            }
          }
        ]
      }
    ],
    "direction": "vertical"
  },
  "left": {
    "id": "cc8c41bc916f5938",
    "type": "split",
    "children": [
      {
        "id": "3a64ad465d2f5401",
        "type": "tabs",
        "children": [
          {
            "id": "89723cd927f44170",
            "type": "leaf",
            "state": {
              "type": "file-explorer",
              "state": {
                "sortOrder": "alphabetical"
              }
            }
          },
          {
            "id": "6026546cdf5cc41e",
            "type": "leaf",
            "state": {
              "type": "search",
              "state": {
                "query": "",
                "matchingCase": false,
                "explainSearch": false,
                "collapseAll": false,
                "extraContext": false,
                "sortOrder": "alphabetical"
              }
            }
          },
          {
            "id": "204361c323ec4564",
            "type": "leaf",
            "state": {
              "type": "bookmarks",
              "state": {}
            }
          }
        ]
      }
    ],
    "direction": "horizontal",
    "width": 300,
    "collapsed": true
  },
  "right": {
    "id": "840cad1b8c897f85",
    "type": "split",
    "children": [
      {
        "id": "73b32622e9b1a3c1",
        "type": "tabs",
        "children": [
          {
            "id": "8dcd4a20d4a390e9",
            "type": "leaf",
            "state": {
              "type": "backlink",
              "state": {
                "file": "Fac/Les bases en C++.md",
                "collapseAll": false,
                "extraContext": false,
                "sortOrder": "alphabetical",
                "showSearch": false,
                "searchQuery": "",
                "backlinkCollapsed": false,
                "unlinkedCollapsed": true
              }
            }
          },
          {
            "id": "0b235a6b0974c246",
            "type": "leaf",
            "state": {
              "type": "outgoing-link",
              "state": {
                "file": "Fac/Les bases en C++.md",
                "linksCollapsed": false,
                "unlinkedCollapsed": true
              }
            }
          },
          {
            "id": "21b11ad31dd0826a",
            "type": "leaf",
            "state": {
              "type": "tag",
              "state": {
                "sortOrder": "frequency",
                "useHierarchy": true
              }
            }
          },
          {
            "id": "ff0920719d01824a",
            "type": "leaf",
            "state": {
              "type": "outline",
              "state": {
                "file": "Fac/Les bases en C++.md"
              }
            }
          },
          {
            "id": "8d60f85a2d30b317",
            "type": "leaf",
            "state": {
              "type": "all-properties",
              "state": {
                "sortOrder": "frequency"
              }
            }
          }
        ]
      }
    ],
    "direction": "horizontal",
    "width": 300,
    "collapsed": true
  },
  "left-ribbon": {
    "hiddenItems": {
      "switcher:Ouvrir le sélecteur rapide": false,
      "graph:Ouvrir la vue graphique": false,
      "canvas:Créer une nouvelle toile": false,
      "daily-notes:Ouvrir la note quotidienne": false,
      "templates:Insérer le modèle": false,
      "command-palette:Ouvrir la palette de commandes": false
    }
  },
  "active": "8dcd4a20d4a390e9",
  "lastOpenFiles": [
    "Fac/Les bases en C++.md",
    "Fac/Les bases du terminal sous macOs, Linux et Windows.md",
    "Fac/Base-Info/Base de l'informatique.md",
    "\".md",
    "code/algo-p1/tp1.cpp",
    "code/algo-p1/ex1.cpp"
  ]
}